aap_ipykernel/__init__.py
aap_ipykernel/__main__.py
aap_ipykernel/__version.py
aap_ipykernel/compat.py
aap_ipykernel/kernel.py
aap_ipykernel/manage.py
aap_ipykernel-1.0.7.dist-info/LICENSE.txt
aap_ipykernel-1.0.7.dist-info/METADATA
aap_ipykernel-1.0.7.dist-info/WHEEL
aap_ipykernel-1.0.7.dist-info/entry_points.txt
aap_ipykernel-1.0.7.dist-info/top_level.txt
aap_ipykernel-1.0.7.dist-info/RECORD
